tk_inter_fr.py
tk_inter_fr-0.0.1.dist-info/LICENSE
tk_inter_fr-0.0.1.dist-info/METADATA
tk_inter_fr-0.0.1.dist-info/WHEEL
tk_inter_fr-0.0.1.dist-info/top_level.txt
tk_inter_fr-0.0.1.dist-info/RECORD
